Metadata-Version: 1.0
Name: ftpservercontext
Version: 2018.2.0
Summary: UNKNOWN
Home-page: https://github.com/tbz-pariv/ftpservercontext
Author: Thomas Guettler
Author-email: guettliml.ftpservercontext@thomas-guettler.de
License: commercial
Platform: UNKNOWN
